{
  "run_id": "2026-06-23_21-53-02_VAE-attn-medium_seed42",
  "timestamp": "2026-06-23T21:53:02.681453",
  "model": "VAE-attn-medium",
  "seed": 42,
  "horizon": 1,
  "signals_meta": {
    "use_set_a": true,
    "use_set_b": true,
    "use_set_c": true
  },
  "position_mode": "cost_aware",
  "cost_bps": 1.0,
  "n_features": 73,
  "n_train": 2642,
  "n_val": 566,
  "n_test": 567,
  "date_test_start": "2024-03-15",
  "date_test_end": "2026-06-18",
  "weights_path": "../data/weights/VAE-attn-medium_h1.pt",
  "metrics": {
    "IC_in": 0.051340174931981584,
    "IC_out": 0.08417007924704316,
    "RankIC_out": -0.009379994138367702,
    "Sharpe_out": 1.133682024881074,
    "AnnRet_out": 0.18101155080036327,
    "position_mode": null,
    "cost_bps": 1.0
  }
}