{
  "run_id": "2026-06-24_15-13-33_abl_h1_A_p_B_p_C_XGBoost_seed42",
  "timestamp": "2026-06-24T15:13:33.058687",
  "model": "abl_h1_A_p_B_p_C_XGBoost",
  "seed": 42,
  "horizon": 1,
  "signals_meta": {
    "use_set_a": true,
    "use_set_b": true,
    "use_set_c": true
  },
  "position_mode": "cost_aware",
  "cost_bps": 1.0,
  "n_features": 73,
  "n_train": 2643,
  "n_val": 566,
  "n_test": 567,
  "date_test_start": "2024-03-18",
  "date_test_end": "2026-06-22",
  "weights_path": "../data/weights/abl_h1_A_p_B_p_C_XGBoost_h1.pt",
  "metrics": {
    "IC_in": 0.6141007238067391,
    "IC_out": 0.18958116495461116,
    "RankIC_out": 0.07220805311124098,
    "Sharpe_out": 1.0809197462936615,
    "AnnRet_out": 0.1727830250972913,
    "position_mode": null,
    "cost_bps": 1.0
  }
}